README.md
setup.py
JBTools/__init__.py
JBTools/evaluate_ocr_results.py
JBTools/neural_language_model_char_based.py
JBTools/simple_proba_language_model_char_based.py
JBTools/tools.py
JBTools.egg-info/PKG-INFO
JBTools.egg-info/SOURCES.txt
JBTools.egg-info/dependency_links.txt
JBTools.egg-info/requires.txt
JBTools.egg-info/top_level.txt