Metadata-Version: 2.1
Name: JBTools
Version: 0.1.1
Summary: My personal packages
Home-page: https://github.com/jbtanguy/JBTools.git
Author: Jean-Baptiste Tanguy
License: MIT
Platform: UNKNOWN
Classifier: Programming Language :: Python :: 3.7
